Metadata-Version: 1.0
Name: projected-sinkhorn
Version: 0.2
Summary: A library implementing the projected sinkhorn iteration for PyTorch
Home-page: https://github.com/locuslab/projected_sinkhorn
Author: Eric Wong
Author-email: ericwong@cs.cmu.edu
License: MIT
Platform: any
